mongodb_connect/__init__.py
mongodb_connect/mongo_crud.py
mongodbautomationpackage-0.0.1.dist-info/METADATA
mongodbautomationpackage-0.0.1.dist-info/WHEEL
mongodbautomationpackage-0.0.1.dist-info/top_level.txt
mongodbautomationpackage-0.0.1.dist-info/RECORD
